[{
    "id": "c:0",
    "name": "Development of vocabulary - Same, different, Top, Bottom, On, Under, Inside, Outside, Above, big, small, Below, Near, Far, Before, After, thick, thin, light, heavy, empty, full, less, more, few,many",
    "games": [{
        "id": "g:48",
        "name": "Game 48",
        "type": "screener"
    }]
}, {
    "id": "c:1",
    "name": "Distinguish Lines (Straight, vertical, horizontal)",
    "games": [{
        "id": "g:30",
        "name": "Game 30",
        "type": "screener"
    }, {
        "id": "g:4",
        "name": "Game 4",
        "type": "game"
    }]
}, {
    "id": "c:2",
    "name": "Draw Lines (Straight, vertical, horizontal)",
    "games": []
}, {
    "id": "c:3",
    "name": "make patterns with lines",
    "games": [{
        "id": "g:14",
        "name": "Game 14",
        "type": "game"
    }, {
        "id": "g:35",
        "name": "Game 35",
        "type": "screener"
    }, {
        "id": "g:10",
        "name": "Game 10",
        "type": "game"
    }, {
        "id": "g:40",
        "name": "Game 40",
        "type": "screener"
    }, {
        "id": "g:28",
        "name": "Game 28",
        "type": "game"
    }]
}, {
    "id": "c:4",
    "name": "Identify simple, symmetrical shapes in patterns",
    "games": [{
        "id": "g:5",
        "name": "Game 5",
        "type": "game"
    }, {
        "id": "g:39",
        "name": "Game 39",
        "type": "screener"
    }, {
        "id": "g:23",
        "name": "Game 23",
        "type": "game"
    }, {
        "id": "g:29",
        "name": "Game 29",
        "type": "game"
    }, {
        "id": "g:43",
        "name": "Game 43",
        "type": "screener"
    }]
}, {
    "id": "c:5",
    "name": "Identify geometrical patterns based on symmetry",
    "games": [{
        "id": "g:27",
        "name": "Game 27",
        "type": "game"
    }]
}, {
    "id": "c:6",
    "name": "Compare shapes",
    "games": [{
        "id": "g:18",
        "name": "Game 18",
        "type": "game"
    }, {
        "id": "g:23",
        "name": "Game 23",
        "type": "game"
    }, {
        "id": "g:1",
        "name": "Game 1",
        "type": "game"
    }, {
        "id": "g:47",
        "name": "Game 47",
        "type": "screener"
    }, {
        "id": "g:32",
        "name": "Game 32",
        "type": "screener"
    }]
}, {
    "id": "c:7",
    "name": "Understand angles through objects/shapes",
    "games": [{
        "id": "g:35",
        "name": "Game 35",
        "type": "screener"
    }, {
        "id": "g:38",
        "name": "Game 38",
        "type": "screener"
    }]
}, {
    "id": "c:8",
    "name": "Identify, classify, draw different Angles : acute, obtuse, and right angles",
    "games": [{
        "id": "g:38",
        "name": "Game 38",
        "type": "screener"
    }]
}, {
    "id": "c:9",
    "name": "Sort 2D shapes",
    "games": [{
        "id": "g:19",
        "name": "Game 19",
        "type": "game"
    }, {
        "id": "g:8",
        "name": "Game 8",
        "type": "game"
    }, {
        "id": "g:47",
        "name": "Game 47",
        "type": "screener"
    }, {
        "id": "g:50",
        "name": "Game 50",
        "type": "screener"
    }, {
        "id": "g:9",
        "name": "Game 9",
        "type": "game"
    }]
}, {
    "id": "c:10",
    "name": "Observe, Identify (by names), Draw 2D shapes",
    "games": [{
        "id": "g:11",
        "name": "Game 11",
        "type": "game"
    }, {
        "id": "g:24",
        "name": "Game 24",
        "type": "game"
    }, {
        "id": "g:1",
        "name": "Game 1",
        "type": "game"
    }, {
        "id": "g:12",
        "name": "Game 12",
        "type": "game"
    }]
}, {
    "id": "c:11",
    "name": "Identify and draw 2D shapes, cut 2D shapes",
    "games": []
}, {
    "id": "c:12",
    "name": "Make shapes using Tangrams; tile an area using shapes",
    "games": [{
        "id": "g:19",
        "name": "Game 19",
        "type": "game"
    }, {
        "id": "g:5",
        "name": "Game 5",
        "type": "game"
    }]
}, {
    "id": "c:13",
    "name": "Drawing circles using compass",
    "games": []
}, {
    "id": "c:14",
    "name": "Identify symmetry in shapes",
    "games": []
}, {
    "id": "c:15",
    "name": "Sequence in patterns using colors, size in shapes, lines, objects - find, describe",
    "games": [{
        "id": "g:42",
        "name": "Game 42",
        "type": "screener"
    }, {
        "id": "g:47",
        "name": "Game 47",
        "type": "screener"
    }, {
        "id": "g:19",
        "name": "Game 19",
        "type": "game"
    }, {
        "id": "g:4",
        "name": "Game 4",
        "type": "game"
    }, {
        "id": "g:30",
        "name": "Game 30",
        "type": "screener"
    }]
}, {
    "id": "c:16",
    "name": "Sequence in patterns using colors, size in shapes, lines, objects - find, complete",
    "games": [{
        "id": "g:40",
        "name": "Game 40",
        "type": "screener"
    }]
}, {
    "id": "c:17",
    "name": "Sequence in patterns using colors, sizes - extend ",
    "games": []
}, {
    "id": "c:18",
    "name": "one to one correspondance in shapes",
    "games": [{
        "id": "g:30",
        "name": "Game 30",
        "type": "screener"
    }, {
        "id": "g:34",
        "name": "Game 34",
        "type": "screener"
    }, {
        "id": "g:39",
        "name": "Game 39",
        "type": "screener"
    }, {
        "id": "g:49",
        "name": "Game 49",
        "type": "screener"
    }, {
        "id": "g:3",
        "name": "Game 3",
        "type": "game"
    }]
}, {
    "id": "c:19",
    "name": "Explores intuitively the reflections through inkblots, paper cutting and paper folding.",
    "games": []
}, {
    "id": "c:20",
    "name": "Explores intuitively rotations and reflections of familiar 2-D shapes",
    "games": [{
        "id": "g:16",
        "name": "Game 16",
        "type": "game"
    }]
}, {
    "id": "c:21",
    "name": "Describe properties intuitively",
    "games": [{
        "id": "g:33",
        "name": "Game 33",
        "type": "screener"
    }, {
        "id": "g:25",
        "name": "Game 25",
        "type": "game"
    }, {
        "id": "g:36",
        "name": "Game 36",
        "type": "screener"
    }, {
        "id": "g:17",
        "name": "Game 17",
        "type": "game"
    }, {
        "id": "g:31",
        "name": "Game 31",
        "type": "screener"
    }]
}, {
    "id": "c:22",
    "name": "Describes and match various 2-D shapes:counting their sides, corners and diagonals, radius and diameter of a circle etc",
    "games": [{
        "id": "g:33",
        "name": "Game 33",
        "type": "screener"
    }, {
        "id": "g:8",
        "name": "Game 8",
        "type": "game"
    }, {
        "id": "g:37",
        "name": "Game 37",
        "type": "screener"
    }, {
        "id": "g:28",
        "name": "Game 28",
        "type": "game"
    }, {
        "id": "g:2",
        "name": "Game 2",
        "type": "game"
    }]
}, {
    "id": "c:23",
    "name": "Understand area and perimeter intuitively",
    "games": [{
        "id": "g:13",
        "name": "Game 13",
        "type": "game"
    }]
}, {
    "id": "c:24",
    "name": "Identify and complete patterns with Colors, shapes",
    "games": [{
        "id": "g:49",
        "name": "Game 49",
        "type": "screener"
    }, {
        "id": "g:27",
        "name": "Game 27",
        "type": "game"
    }, {
        "id": "g:33",
        "name": "Game 33",
        "type": "screener"
    }, {
        "id": "g:17",
        "name": "Game 17",
        "type": "game"
    }]
}, {
    "id": "c:25",
    "name": "Distinguish objects from surroundings based on size and shape",
    "games": [{
        "id": "g:4",
        "name": "Game 4",
        "type": "game"
    }, {
        "id": "g:14",
        "name": "Game 14",
        "type": "game"
    }, {
        "id": "g:23",
        "name": "Game 23",
        "type": "game"
    }, {
        "id": "g:25",
        "name": "Game 25",
        "type": "game"
    }, {
        "id": "g:15",
        "name": "Game 15",
        "type": "game"
    }]
}, {
    "id": "c:26",
    "name": "Identify and observe 3D objects by names ",
    "games": [{
        "id": "g:12",
        "name": "Game 12",
        "type": "game"
    }, {
        "id": "g:39",
        "name": "Game 39",
        "type": "screener"
    }]
}, {
    "id": "c:27",
    "name": "Draw 3D objects",
    "games": [{
        "id": "g:33",
        "name": "Game 33",
        "type": "screener"
    }, {
        "id": "g:42",
        "name": "Game 42",
        "type": "screener"
    }, {
        "id": "g:17",
        "name": "Game 17",
        "type": "game"
    }, {
        "id": "g:47",
        "name": "Game 47",
        "type": "screener"
    }]
}, {
    "id": "c:28",
    "name": "Make objects (cubes) using nets etc.",
    "games": [{
        "id": "g:24",
        "name": "Game 24",
        "type": "game"
    }]
}, {
    "id": "c:29",
    "name": "Make objects (cylinders, cones) using nets etc.",
    "games": [{
        "id": "g:4",
        "name": "Game 4",
        "type": "game"
    }, {
        "id": "g:26",
        "name": "Game 26",
        "type": "game"
    }, {
        "id": "g:32",
        "name": "Game 32",
        "type": "screener"
    }, {
        "id": "g:20",
        "name": "Game 20",
        "type": "game"
    }, {
        "id": "g:37",
        "name": "Game 37",
        "type": "screener"
    }]
}, {
    "id": "c:30",
    "name": "Symmetry in 3D shapes",
    "games": [{
        "id": "g:50",
        "name": "Game 50",
        "type": "screener"
    }, {
        "id": "g:26",
        "name": "Game 26",
        "type": "game"
    }, {
        "id": "g:49",
        "name": "Game 49",
        "type": "screener"
    }]
}, {
    "id": "c:31",
    "name": "Order containers based on capacities/size",
    "games": [{
        "id": "g:27",
        "name": "Game 27",
        "type": "game"
    }, {
        "id": "g:21",
        "name": "Game 21",
        "type": "game"
    }, {
        "id": "g:24",
        "name": "Game 24",
        "type": "game"
    }, {
        "id": "g:1",
        "name": "Game 1",
        "type": "game"
    }, {
        "id": "g:29",
        "name": "Game 29",
        "type": "game"
    }]
}, {
    "id": "c:32",
    "name": "Observes and describes the way shapes affect movements like rolling and sliding",
    "games": [{
        "id": "g:4",
        "name": "Game 4",
        "type": "game"
    }]
}, {
    "id": "c:33",
    "name": "Understand volume of solid body",
    "games": [{
        "id": "g:42",
        "name": "Game 42",
        "type": "screener"
    }]
}, {
    "id": "c:34",
    "name": "Compare light/heavy objects",
    "games": [{
        "id": "g:38",
        "name": "Game 38",
        "type": "screener"
    }, {
        "id": "g:28",
        "name": "Game 28",
        "type": "game"
    }]
}, {
    "id": "c:35",
    "name": "Compares two or more objects by their weight",
    "games": [{
        "id": "g:35",
        "name": "Game 35",
        "type": "screener"
    }, {
        "id": "g:49",
        "name": "Game 49",
        "type": "screener"
    }, {
        "id": "g:14",
        "name": "Game 14",
        "type": "game"
    }, {
        "id": "g:32",
        "name": "Game 32",
        "type": "screener"
    }, {
        "id": "g:19",
        "name": "Game 19",
        "type": "game"
    }]
}, {
    "id": "c:36",
    "name": "Trace 2-D outlines of 3-D shapes",
    "games": [{
        "id": "g:27",
        "name": "Game 27",
        "type": "game"
    }, {
        "id": "g:10",
        "name": "Game 10",
        "type": "game"
    }]
}, {
    "id": "c:37",
    "name": "Identifies objects by observing their shadows",
    "games": [{
        "id": "g:32",
        "name": "Game 32",
        "type": "screener"
    }, {
        "id": "g:28",
        "name": "Game 28",
        "type": "game"
    }, {
        "id": "g:45",
        "name": "Game 45",
        "type": "screener"
    }, {
        "id": "g:29",
        "name": "Game 29",
        "type": "game"
    }, {
        "id": "g:9",
        "name": "Game 9",
        "type": "game"
    }]
}, {
    "id": "c:38",
    "name": "Read 3D objects; Draws intuitively the plan, elevation and side view of simple objects.",
    "games": [{
        "id": "g:25",
        "name": "Game 25",
        "type": "game"
    }, {
        "id": "g:37",
        "name": "Game 37",
        "type": "screener"
    }, {
        "id": "g:45",
        "name": "Game 45",
        "type": "screener"
    }, {
        "id": "g:47",
        "name": "Game 47",
        "type": "screener"
    }, {
        "id": "g:35",
        "name": "Game 35",
        "type": "screener"
    }]
}, {
    "id": "c:39",
    "name": "Gets the feel of perspective while drawing a 3-D object in 2-D.",
    "games": [{
        "id": "g:36",
        "name": "Game 36",
        "type": "screener"
    }, {
        "id": "g:30",
        "name": "Game 30",
        "type": "screener"
    }, {
        "id": "g:49",
        "name": "Game 49",
        "type": "screener"
    }]
}, {
    "id": "c:40",
    "name": "Observe and make collections of objects",
    "games": [{
        "id": "g:7",
        "name": "Game 7",
        "type": "game"
    }, {
        "id": "g:43",
        "name": "Game 43",
        "type": "screener"
    }, {
        "id": "g:38",
        "name": "Game 38",
        "type": "screener"
    }, {
        "id": "g:11",
        "name": "Game 11",
        "type": "game"
    }]
}, {
    "id": "c:41",
    "name": "Count objects upto 20",
    "games": [{
        "id": "g:49",
        "name": "Game 49",
        "type": "screener"
    }, {
        "id": "g:36",
        "name": "Game 36",
        "type": "screener"
    }, {
        "id": "g:27",
        "name": "Game 27",
        "type": "game"
    }, {
        "id": "g:15",
        "name": "Game 15",
        "type": "game"
    }, {
        "id": "g:14",
        "name": "Game 14",
        "type": "game"
    }]
}, {
    "id": "c:42",
    "name": "Ordering (using objects) upto 20",
    "games": [{
        "id": "g:1",
        "name": "Game 1",
        "type": "game"
    }, {
        "id": "g:7",
        "name": "Game 7",
        "type": "game"
    }, {
        "id": "g:14",
        "name": "Game 14",
        "type": "game"
    }, {
        "id": "g:4",
        "name": "Game 4",
        "type": "game"
    }]
}, {
    "id": "c:43",
    "name": "Use objects for one to one correspondance",
    "games": [{
        "id": "g:37",
        "name": "Game 37",
        "type": "screener"
    }, {
        "id": "g:19",
        "name": "Game 19",
        "type": "game"
    }, {
        "id": "g:2",
        "name": "Game 2",
        "type": "game"
    }, {
        "id": "g:35",
        "name": "Game 35",
        "type": "screener"
    }]
}, {
    "id": "c:44",
    "name": "collections of objects matching to numbers",
    "games": [{
        "id": "g:17",
        "name": "Game 17",
        "type": "game"
    }, {
        "id": "g:3",
        "name": "Game 3",
        "type": "game"
    }]
}, {
    "id": "c:45",
    "name": "understand eqality of sets with equal number of objects",
    "games": [{
        "id": "g:2",
        "name": "Game 2",
        "type": "game"
    }, {
        "id": "g:35",
        "name": "Game 35",
        "type": "screener"
    }]
}, {
    "id": "c:46",
    "name": "Counting from any number - upto 99",
    "games": [{
        "id": "g:41",
        "name": "Game 41",
        "type": "screener"
    }, {
        "id": "g:11",
        "name": "Game 11",
        "type": "game"
    }]
}, {
    "id": "c:47",
    "name": "Counting in different ways - starting from any number upto 1000",
    "games": [{
        "id": "g:10",
        "name": "Game 10",
        "type": "game"
    }, {
        "id": "g:39",
        "name": "Game 39",
        "type": "screener"
    }, {
        "id": "g:29",
        "name": "Game 29",
        "type": "game"
    }, {
        "id": "g:5",
        "name": "Game 5",
        "type": "game"
    }, {
        "id": "g:26",
        "name": "Game 26",
        "type": "game"
    }]
}, {
    "id": "c:48",
    "name": "Map quantities to numbers: Use real objects, claps, etc. to count",
    "games": [{
        "id": "g:10",
        "name": "Game 10",
        "type": "game"
    }, {
        "id": "g:38",
        "name": "Game 38",
        "type": "screener"
    }, {
        "id": "g:26",
        "name": "Game 26",
        "type": "game"
    }]
}, {
    "id": "c:49",
    "name": "Decode 0-9, 10-99",
    "games": [{
        "id": "g:22",
        "name": "Game 22",
        "type": "game"
    }]
}, {
    "id": "c:50",
    "name": "Decode Upto 99",
    "games": [{
        "id": "g:39",
        "name": "Game 39",
        "type": "screener"
    }, {
        "id": "g:14",
        "name": "Game 14",
        "type": "game"
    }, {
        "id": "g:8",
        "name": "Game 8",
        "type": "game"
    }, {
        "id": "g:44",
        "name": "Game 44",
        "type": "screener"
    }, {
        "id": "g:21",
        "name": "Game 21",
        "type": "game"
    }]
}, {
    "id": "c:51",
    "name": "Decode upto 1000",
    "games": [{
        "id": "g:30",
        "name": "Game 30",
        "type": "screener"
    }, {
        "id": "g:2",
        "name": "Game 2",
        "type": "game"
    }, {
        "id": "g:34",
        "name": "Game 34",
        "type": "screener"
    }, {
        "id": "g:48",
        "name": "Game 48",
        "type": "screener"
    }]
}, {
    "id": "c:52",
    "name": "compare using numbers: 0 to 20",
    "games": [{
        "id": "g:18",
        "name": "Game 18",
        "type": "game"
    }, {
        "id": "g:29",
        "name": "Game 29",
        "type": "game"
    }, {
        "id": "g:17",
        "name": "Game 17",
        "type": "game"
    }, {
        "id": "g:38",
        "name": "Game 38",
        "type": "screener"
    }]
}, {
    "id": "c:53",
    "name": "Form the greatest and smallest two digit numbers with and without repetition of digits upto 100",
    "games": [{
        "id": "g:28",
        "name": "Game 28",
        "type": "game"
    }, {
        "id": "g:13",
        "name": "Game 13",
        "type": "game"
    }, {
        "id": "g:4",
        "name": "Game 4",
        "type": "game"
    }, {
        "id": "g:2",
        "name": "Game 2",
        "type": "game"
    }]
}, {
    "id": "c:54",
    "name": "Compare numbers upto 1000",
    "games": [{
        "id": "g:19",
        "name": "Game 19",
        "type": "game"
    }]
}, {
    "id": "c:55",
    "name": "Form the greatest and smallest three digit numbers with and without repetition of digits upto 1000",
    "games": [{
        "id": "g:30",
        "name": "Game 30",
        "type": "screener"
    }, {
        "id": "g:4",
        "name": "Game 4",
        "type": "game"
    }, {
        "id": "g:1",
        "name": "Game 1",
        "type": "game"
    }, {
        "id": "g:14",
        "name": "Game 14",
        "type": "game"
    }]
}, {
    "id": "c:56",
    "name": "Ascending & descending order,skip counting, additive reasoning upto 100",
    "games": [{
        "id": "g:30",
        "name": "Game 30",
        "type": "screener"
    }, {
        "id": "g:35",
        "name": "Game 35",
        "type": "screener"
    }]
}, {
    "id": "c:57",
    "name": "whole part relationship, stable order, order irrelevance upto 100",
    "games": []
}, {
    "id": "c:58",
    "name": "Indicates and identifies the position of an object in a line",
    "games": [{
        "id": "g:15",
        "name": "Game 15",
        "type": "game"
    }, {
        "id": "g:6",
        "name": "Game 6",
        "type": "game"
    }]
}, {
    "id": "c:59",
    "name": "Sequencing, additive reasoning and skip counting upto 1000",
    "games": [{
        "id": "g:9",
        "name": "Game 9",
        "type": "game"
    }, {
        "id": "g:36",
        "name": "Game 36",
        "type": "screener"
    }]
}, {
    "id": "c:60",
    "name": "Understand patterns in odd and even numbers ",
    "games": [{
        "id": "g:45",
        "name": "Game 45",
        "type": "screener"
    }, {
        "id": "g:20",
        "name": "Game 20",
        "type": "game"
    }, {
        "id": "g:33",
        "name": "Game 33",
        "type": "screener"
    }, {
        "id": "g:2",
        "name": "Game 2",
        "type": "game"
    }]
}, {
    "id": "c:61",
    "name": "Partition a number in different ways",
    "games": [{
        "id": "g:7",
        "name": "Game 7",
        "type": "game"
    }, {
        "id": "g:26",
        "name": "Game 26",
        "type": "game"
    }, {
        "id": "g:25",
        "name": "Game 25",
        "type": "game"
    }, {
        "id": "g:28",
        "name": "Game 28",
        "type": "game"
    }, {
        "id": "g:48",
        "name": "Game 48",
        "type": "screener"
    }]
}, {
    "id": "c:62",
    "name": "identify pattens in square numbers and triangular numbers",
    "games": []
}, {
    "id": "c:63",
    "name": "relates sequences of odd numbers between consecutive square numbers",
    "games": [{
        "id": "g:39",
        "name": "Game 39",
        "type": "screener"
    }, {
        "id": "g:8",
        "name": "Game 8",
        "type": "game"
    }, {
        "id": "g:26",
        "name": "Game 26",
        "type": "game"
    }, {
        "id": "g:16",
        "name": "Game 16",
        "type": "game"
    }]
}, {
    "id": "c:64",
    "name": "Idenitfy numbers on a mental number line",
    "games": [{
        "id": "g:19",
        "name": "Game 19",
        "type": "game"
    }, {
        "id": "g:37",
        "name": "Game 37",
        "type": "screener"
    }, {
        "id": "g:16",
        "name": "Game 16",
        "type": "game"
    }, {
        "id": "g:30",
        "name": "Game 30",
        "type": "screener"
    }]
}, {
    "id": "c:65",
    "name": "Use vocabulary of tens and ones",
    "games": [{
        "id": "g:5",
        "name": "Game 5",
        "type": "game"
    }, {
        "id": "g:4",
        "name": "Game 4",
        "type": "game"
    }, {
        "id": "g:25",
        "name": "Game 25",
        "type": "game"
    }, {
        "id": "g:29",
        "name": "Game 29",
        "type": "game"
    }, {
        "id": "g:19",
        "name": "Game 19",
        "type": "game"
    }]
}, {
    "id": "c:66",
    "name": "Understand tens and ones upto 99 by grouping objects, drawing into tens and ones",
    "games": [{
        "id": "g:35",
        "name": "Game 35",
        "type": "screener"
    }]
}, {
    "id": "c:67",
    "name": "Understand tens and ones upto 99: count and group objects",
    "games": [{
        "id": "g:36",
        "name": "Game 36",
        "type": "screener"
    }, {
        "id": "g:29",
        "name": "Game 29",
        "type": "game"
    }, {
        "id": "g:38",
        "name": "Game 38",
        "type": "screener"
    }, {
        "id": "g:43",
        "name": "Game 43",
        "type": "screener"
    }]
}, {
    "id": "c:68",
    "name": "Comparison of numbers using place value",
    "games": [{
        "id": "g:14",
        "name": "Game 14",
        "type": "game"
    }, {
        "id": "g:1",
        "name": "Game 1",
        "type": "game"
    }, {
        "id": "g:35",
        "name": "Game 35",
        "type": "screener"
    }, {
        "id": "g:40",
        "name": "Game 40",
        "type": "screener"
    }, {
        "id": "g:18",
        "name": "Game 18",
        "type": "game"
    }]
}, {
    "id": "c:69",
    "name": " Expansion (expand a number with respect to place values) upto 99",
    "games": [{
        "id": "g:22",
        "name": "Game 22",
        "type": "game"
    }]
}, {
    "id": "c:70",
    "name": "Expansion of numbers upto 1000",
    "games": [{
        "id": "g:26",
        "name": "Game 26",
        "type": "game"
    }, {
        "id": "g:48",
        "name": "Game 48",
        "type": "screener"
    }, {
        "id": "g:39",
        "name": "Game 39",
        "type": "screener"
    }, {
        "id": "g:8",
        "name": "Game 8",
        "type": "game"
    }, {
        "id": "g:32",
        "name": "Game 32",
        "type": "screener"
    }]
}, {
    "id": "c:71",
    "name": "upto 1000",
    "games": [{
        "id": "g:3",
        "name": "Game 3",
        "type": "game"
    }]
}, {
    "id": "c:72",
    "name": "Beyond 1000",
    "games": []
}, {
    "id": "c:73",
    "name": "Estimation of sum/difference and compare with numbers",
    "games": [{
        "id": "g:7",
        "name": "Game 7",
        "type": "game"
    }, {
        "id": "g:22",
        "name": "Game 22",
        "type": "game"
    }]
}, {
    "id": "c:74",
    "name": "Estimation of sum/difference",
    "games": [{
        "id": "g:42",
        "name": "Game 42",
        "type": "screener"
    }, {
        "id": "g:26",
        "name": "Game 26",
        "type": "game"
    }, {
        "id": "g:14",
        "name": "Game 14",
        "type": "game"
    }, {
        "id": "g:15",
        "name": "Game 15",
        "type": "game"
    }, {
        "id": "g:13",
        "name": "Game 13",
        "type": "game"
    }]
}, {
    "id": "c:75",
    "name": "Estimation of sum/difference/product",
    "games": [{
        "id": "g:41",
        "name": "Game 41",
        "type": "screener"
    }, {
        "id": "g:8",
        "name": "Game 8",
        "type": "game"
    }, {
        "id": "g:22",
        "name": "Game 22",
        "type": "game"
    }, {
        "id": "g:39",
        "name": "Game 39",
        "type": "screener"
    }, {
        "id": "g:1",
        "name": "Game 1",
        "type": "game"
    }]
}, {
    "id": "c:76",
    "name": "Estimation of sum/difference/product/quotient and verification by approximation",
    "games": [{
        "id": "g:15",
        "name": "Game 15",
        "type": "game"
    }, {
        "id": "g:20",
        "name": "Game 20",
        "type": "game"
    }]
}, {
    "id": "c:77",
    "name": "Through objects",
    "games": []
}, {
    "id": "c:78",
    "name": "Use addition/subtraction symbols",
    "games": [{
        "id": "g:25",
        "name": "Game 25",
        "type": "game"
    }, {
        "id": "g:31",
        "name": "Game 31",
        "type": "screener"
    }, {
        "id": "g:43",
        "name": "Game 43",
        "type": "screener"
    }]
}, {
    "id": "c:79",
    "name": "Through representations of 1s and 10s",
    "games": [{
        "id": "g:1",
        "name": "Game 1",
        "type": "game"
    }]
}, {
    "id": "c:80",
    "name": "Write numbers vertically (without grouping)",
    "games": [{
        "id": "g:3",
        "name": "Game 3",
        "type": "game"
    }, {
        "id": "g:31",
        "name": "Game 31",
        "type": "screener"
    }, {
        "id": "g:4",
        "name": "Game 4",
        "type": "game"
    }, {
        "id": "g:33",
        "name": "Game 33",
        "type": "screener"
    }, {
        "id": "g:9",
        "name": "Game 9",
        "type": "game"
    }]
}, {
    "id": "c:81",
    "name": "Understand 0 using addition/subtraction",
    "games": [{
        "id": "g:32",
        "name": "Game 32",
        "type": "screener"
    }, {
        "id": "g:23",
        "name": "Game 23",
        "type": "game"
    }, {
        "id": "g:16",
        "name": "Game 16",
        "type": "game"
    }, {
        "id": "g:18",
        "name": "Game 18",
        "type": "game"
    }]
}, {
    "id": "c:82",
    "name": "Add subtract using column addition without grouping (using place value)",
    "games": [{
        "id": "g:19",
        "name": "Game 19",
        "type": "game"
    }]
}, {
    "id": "c:83",
    "name": "Two digit numbers, addition upto 99 (grouping)",
    "games": [{
        "id": "g:38",
        "name": "Game 38",
        "type": "screener"
    }]
}, {
    "id": "c:84",
    "name": "addition and subtraction upto 1000 (grouping)",
    "games": [{
        "id": "g:22",
        "name": "Game 22",
        "type": "game"
    }]
}, {
    "id": "c:85",
    "name": "addition and subtraction upto 1000 (grouping) using place value",
    "games": [{
        "id": "g:25",
        "name": "Game 25",
        "type": "game"
    }, {
        "id": "g:19",
        "name": "Game 19",
        "type": "game"
    }, {
        "id": "g:43",
        "name": "Game 43",
        "type": "screener"
    }]
}, {
    "id": "c:86",
    "name": "Write numbers vertically (with grouping)",
    "games": [{
        "id": "g:35",
        "name": "Game 35",
        "type": "screener"
    }]
}, {
    "id": "c:87",
    "name": "Use operations to find total change, multiple costs and unit costs",
    "games": [{
        "id": "g:21",
        "name": "Game 21",
        "type": "game"
    }, {
        "id": "g:25",
        "name": "Game 25",
        "type": "game"
    }]
}, {
    "id": "c:88",
    "name": "Addition as inverse of subtraction  - get to 0 using addition/subtraction using objects",
    "games": []
}, {
    "id": "c:89",
    "name": "Mental maths; Single digit, ",
    "games": [{
        "id": "g:36",
        "name": "Game 36",
        "type": "screener"
    }]
}, {
    "id": "c:90",
    "name": "Mental maths; Single digit, multiples of 10",
    "games": [{
        "id": "g:20",
        "name": "Game 20",
        "type": "game"
    }, {
        "id": "g:16",
        "name": "Game 16",
        "type": "game"
    }, {
        "id": "g:48",
        "name": "Game 48",
        "type": "screener"
    }]
}, {
    "id": "c:91",
    "name": "Mental Maths : Two digits numbers",
    "games": []
}, {
    "id": "c:92",
    "name": "Doubles two digit number mentally",
    "games": [{
        "id": "g:20",
        "name": "Game 20",
        "type": "game"
    }, {
        "id": "g:16",
        "name": "Game 16",
        "type": "game"
    }]
}, {
    "id": "c:93",
    "name": "Add and subtract multiples of 10s and 100s mentally",
    "games": [{
        "id": "g:25",
        "name": "Game 25",
        "type": "game"
    }, {
        "id": "g:44",
        "name": "Game 44",
        "type": "screener"
    }, {
        "id": "g:26",
        "name": "Game 26",
        "type": "game"
    }]
}, {
    "id": "c:94",
    "name": "Complete multiplication facts by adding partial products ( 7 x 6 = 5 x 6 + 2 x 6)",
    "games": [{
        "id": "g:31",
        "name": "Game 31",
        "type": "screener"
    }, {
        "id": "g:28",
        "name": "Game 28",
        "type": "game"
    }]
}, {
    "id": "c:95",
    "name": "Determine sum and difference of weights",
    "games": [{
        "id": "g:28",
        "name": "Game 28",
        "type": "game"
    }, {
        "id": "g:23",
        "name": "Game 23",
        "type": "game"
    }, {
        "id": "g:21",
        "name": "Game 21",
        "type": "game"
    }, {
        "id": "g:9",
        "name": "Game 9",
        "type": "game"
    }]
}, {
    "id": "c:96",
    "name": "Understand meaning of multiplication (as repeated addition, combination of units, etc.)",
    "games": []
}, {
    "id": "c:97",
    "name": "Understand symbols",
    "games": [{
        "id": "g:6",
        "name": "Game 6",
        "type": "game"
    }, {
        "id": "g:17",
        "name": "Game 17",
        "type": "game"
    }]
}, {
    "id": "c:98",
    "name": "Use multiplication facts in situations",
    "games": []
}, {
    "id": "c:99",
    "name": "Multiplication of 2 digits",
    "games": [{
        "id": "g:47",
        "name": "Game 47",
        "type": "screener"
    }, {
        "id": "g:50",
        "name": "Game 50",
        "type": "screener"
    }]
}, {
    "id": "c:100",
    "name": "Multiplication of 2 digits, 3 digits ",
    "games": []
}, {
    "id": "c:101",
    "name": "Understand role of place value in multiplication",
    "games": [{
        "id": "g:14",
        "name": "Game 14",
        "type": "game"
    }, {
        "id": "g:48",
        "name": "Game 48",
        "type": "screener"
    }, {
        "id": "g:13",
        "name": "Game 13",
        "type": "game"
    }]
}, {
    "id": "c:102",
    "name": "Mathematical tables of 2,3,4,5,10 (understand, learn)",
    "games": [{
        "id": "g:27",
        "name": "Game 27",
        "type": "game"
    }, {
        "id": "g:35",
        "name": "Game 35",
        "type": "screener"
    }, {
        "id": "g:24",
        "name": "Game 24",
        "type": "game"
    }, {
        "id": "g:10",
        "name": "Game 10",
        "type": "game"
    }, {
        "id": "g:46",
        "name": "Game 46",
        "type": "screener"
    }]
}, {
    "id": "c:103",
    "name": "Mathematical tables upto 10 (understand, learn, write)",
    "games": [{
        "id": "g:29",
        "name": "Game 29",
        "type": "game"
    }]
}, {
    "id": "c:104",
    "name": "Multiply 10's and 100's ",
    "games": [{
        "id": "g:35",
        "name": "Game 35",
        "type": "screener"
    }, {
        "id": "g:19",
        "name": "Game 19",
        "type": "game"
    }, {
        "id": "g:48",
        "name": "Game 48",
        "type": "screener"
    }, {
        "id": "g:20",
        "name": "Game 20",
        "type": "game"
    }]
}, {
    "id": "c:105",
    "name": "Meaning of division in the context of equal grouping and sharing by objects",
    "games": [{
        "id": "g:36",
        "name": "Game 36",
        "type": "screener"
    }, {
        "id": "g:44",
        "name": "Game 44",
        "type": "screener"
    }]
}, {
    "id": "c:106",
    "name": "Relate division with mulitplication through examples",
    "games": [{
        "id": "g:29",
        "name": "Game 29",
        "type": "game"
    }]
}, {
    "id": "c:107",
    "name": "drawing dots",
    "games": [{
        "id": "g:25",
        "name": "Game 25",
        "type": "game"
    }, {
        "id": "g:11",
        "name": "Game 11",
        "type": "game"
    }, {
        "id": "g:27",
        "name": "Game 27",
        "type": "game"
    }]
}, {
    "id": "c:108",
    "name": "grouping",
    "games": [{
        "id": "g:7",
        "name": "Game 7",
        "type": "game"
    }, {
        "id": "g:3",
        "name": "Game 3",
        "type": "game"
    }, {
        "id": "g:6",
        "name": "Game 6",
        "type": "game"
    }]
}, {
    "id": "c:109",
    "name": "inverse of multiplication",
    "games": [{
        "id": "g:26",
        "name": "Game 26",
        "type": "game"
    }, {
        "id": "g:38",
        "name": "Game 38",
        "type": "screener"
    }]
}, {
    "id": "c:110",
    "name": "repeated subtraction",
    "games": []
}, {
    "id": "c:111",
    "name": "divide by 10s and 100s",
    "games": [{
        "id": "g:15",
        "name": "Game 15",
        "type": "game"
    }, {
        "id": "g:7",
        "name": "Game 7",
        "type": "game"
    }, {
        "id": "g:30",
        "name": "Game 30",
        "type": "screener"
    }]
}, {
    "id": "c:112",
    "name": "multiplication tables",
    "games": [{
        "id": "g:2",
        "name": "Game 2",
        "type": "game"
    }, {
        "id": "g:26",
        "name": "Game 26",
        "type": "game"
    }]
}, {
    "id": "c:113",
    "name": "Use informal and standard division algorithm",
    "games": [{
        "id": "g:35",
        "name": "Game 35",
        "type": "screener"
    }, {
        "id": "g:41",
        "name": "Game 41",
        "type": "screener"
    }, {
        "id": "g:28",
        "name": "Game 28",
        "type": "game"
    }, {
        "id": "g:34",
        "name": "Game 34",
        "type": "screener"
    }, {
        "id": "g:2",
        "name": "Game 2",
        "type": "game"
    }]
}, {
    "id": "c:114",
    "name": "Identify patterns in multiples of 9 in multiplication and division",
    "games": [{
        "id": "g:22",
        "name": "Game 22",
        "type": "game"
    }, {
        "id": "g:25",
        "name": "Game 25",
        "type": "game"
    }, {
        "id": "g:2",
        "name": "Game 2",
        "type": "game"
    }, {
        "id": "g:34",
        "name": "Game 34",
        "type": "screener"
    }, {
        "id": "g:35",
        "name": "Game 35",
        "type": "screener"
    }]
}, {
    "id": "c:115",
    "name": "Identify patterns in multiplication with and dividing by 10",
    "games": []
}, {
    "id": "c:116",
    "name": "Explain the meaning of factors and multiples",
    "games": [{
        "id": "g:41",
        "name": "Game 41",
        "type": "screener"
    }, {
        "id": "g:32",
        "name": "Game 32",
        "type": "screener"
    }, {
        "id": "g:17",
        "name": "Game 17",
        "type": "game"
    }]
}, {
    "id": "c:117",
    "name": "Estimate products and quotients and verify using approximation; adding partial products, multiplication  in mind",
    "games": [{
        "id": "g:35",
        "name": "Game 35",
        "type": "screener"
    }, {
        "id": "g:23",
        "name": "Game 23",
        "type": "game"
    }]
}, {
    "id": "c:118",
    "name": "Learn and use the rules",
    "games": [{
        "id": "g:23",
        "name": "Game 23",
        "type": "game"
    }, {
        "id": "g:45",
        "name": "Game 45",
        "type": "screener"
    }, {
        "id": "g:39",
        "name": "Game 39",
        "type": "screener"
    }, {
        "id": "g:22",
        "name": "Game 22",
        "type": "game"
    }, {
        "id": "g:20",
        "name": "Game 20",
        "type": "game"
    }]
}, {
    "id": "c:119",
    "name": "Apply add/subtract/multiply operations operations in solving length, weight and volume problems",
    "games": [{
        "id": "g:4",
        "name": "Game 4",
        "type": "game"
    }, {
        "id": "g:22",
        "name": "Game 22",
        "type": "game"
    }]
}, {
    "id": "c:120",
    "name": "Four operations using length, volume, weight",
    "games": [{
        "id": "g:50",
        "name": "Game 50",
        "type": "screener"
    }, {
        "id": "g:3",
        "name": "Game 3",
        "type": "game"
    }, {
        "id": "g:47",
        "name": "Game 47",
        "type": "screener"
    }]
}, {
    "id": "c:121",
    "name": "Use addition and subtraction problems is different situations presented in pictures and stories",
    "games": [{
        "id": "g:15",
        "name": "Game 15",
        "type": "game"
    }, {
        "id": "g:26",
        "name": "Game 26",
        "type": "game"
    }]
}, {
    "id": "c:122",
    "name": "frame problems for addition and subtraction facts",
    "games": []
}, {
    "id": "c:123",
    "name": "Frame word problems",
    "games": [{
        "id": "g:27",
        "name": "Game 27",
        "type": "game"
    }, {
        "id": "g:10",
        "name": "Game 10",
        "type": "game"
    }]
}, {
    "id": "c:124",
    "name": "Understand fractions and decimals in context of time, distance, weight ",
    "games": [{
        "id": "g:9",
        "name": "Game 9",
        "type": "game"
    }]
}, {
    "id": "c:125",
    "name": "Notations of fractions, Identify symbols : 1/2, 1/4 and 3/4",
    "games": [{
        "id": "g:26",
        "name": "Game 26",
        "type": "game"
    }]
}, {
    "id": "c:126",
    "name": "Identifies and explains half, one fourth and three - fourths, etc. Understand fraction as part of a collection etc.",
    "games": [{
        "id": "g:34",
        "name": "Game 34",
        "type": "screener"
    }]
}, {
    "id": "c:127",
    "name": "Apply quantities to fractions",
    "games": [{
        "id": "g:41",
        "name": "Game 41",
        "type": "screener"
    }, {
        "id": "g:5",
        "name": "Game 5",
        "type": "game"
    }, {
        "id": "g:7",
        "name": "Game 7",
        "type": "game"
    }]
}, {
    "id": "c:128",
    "name": "understand equivalence of 1/2 and 2/4, 2/2 , 3/3, 4/4 and 1",
    "games": []
}, {
    "id": "c:129",
    "name": "find fractional part of a collection",
    "games": [{
        "id": "g:44",
        "name": "Game 44",
        "type": "screener"
    }, {
        "id": "g:33",
        "name": "Game 33",
        "type": "screener"
    }, {
        "id": "g:42",
        "name": "Game 42",
        "type": "screener"
    }, {
        "id": "g:22",
        "name": "Game 22",
        "type": "game"
    }, {
        "id": "g:43",
        "name": "Game 43",
        "type": "screener"
    }]
}, {
    "id": "c:130",
    "name": "use decimal fractions for length ",
    "games": [{
        "id": "g:48",
        "name": "Game 48",
        "type": "screener"
    }, {
        "id": "g:2",
        "name": "Game 2",
        "type": "game"
    }, {
        "id": "g:43",
        "name": "Game 43",
        "type": "screener"
    }]
}, {
    "id": "c:131",
    "name": "convert fraction to decimal and vise versa",
    "games": [{
        "id": "g:45",
        "name": "Game 45",
        "type": "screener"
    }, {
        "id": "g:28",
        "name": "Game 28",
        "type": "game"
    }]
}, {
    "id": "c:132",
    "name": "Estimates the degree of closeness of a fraction to known fractions(1/4,1/2,3/4)",
    "games": [{
        "id": "g:47",
        "name": "Game 47",
        "type": "screener"
    }, {
        "id": "g:15",
        "name": "Game 15",
        "type": "game"
    }, {
        "id": "g:16",
        "name": "Game 16",
        "type": "game"
    }]
}, {
    "id": "c:133",
    "name": "Identify equivalent fractions",
    "games": []
}, {
    "id": "c:134",
    "name": "Measurement with non standard metric - seriate length, non standard units",
    "games": []
}, {
    "id": "c:135",
    "name": "Measurement with  standard metric, standard units",
    "games": [{
        "id": "g:18",
        "name": "Game 18",
        "type": "game"
    }, {
        "id": "g:36",
        "name": "Game 36",
        "type": "screener"
    }, {
        "id": "g:43",
        "name": "Game 43",
        "type": "screener"
    }, {
        "id": "g:20",
        "name": "Game 20",
        "type": "game"
    }, {
        "id": "g:48",
        "name": "Game 48",
        "type": "screener"
    }]
}, {
    "id": "c:136",
    "name": "Measurement with non standard units",
    "games": [{
        "id": "g:38",
        "name": "Game 38",
        "type": "screener"
    }, {
        "id": "g:36",
        "name": "Game 36",
        "type": "screener"
    }, {
        "id": "g:11",
        "name": "Game 11",
        "type": "game"
    }]
}, {
    "id": "c:137",
    "name": "Estimate length, verify in standard units",
    "games": [{
        "id": "g:33",
        "name": "Game 33",
        "type": "screener"
    }]
}, {
    "id": "c:138",
    "name": "Learn to use a ruler",
    "games": [{
        "id": "g:49",
        "name": "Game 49",
        "type": "screener"
    }, {
        "id": "g:26",
        "name": "Game 26",
        "type": "game"
    }, {
        "id": "g:3",
        "name": "Game 3",
        "type": "game"
    }]
}, {
    "id": "c:139",
    "name": "Understanding the Metric system : relate cm and metre, convert cm to metre and vice versa",
    "games": [{
        "id": "g:31",
        "name": "Game 31",
        "type": "screener"
    }, {
        "id": "g:21",
        "name": "Game 21",
        "type": "game"
    }, {
        "id": "g:30",
        "name": "Game 30",
        "type": "screener"
    }, {
        "id": "g:36",
        "name": "Game 36",
        "type": "screener"
    }, {
        "id": "g:19",
        "name": "Game 19",
        "type": "game"
    }]
}, {
    "id": "c:140",
    "name": "Solve problems involving length and distance",
    "games": [{
        "id": "g:25",
        "name": "Game 25",
        "type": "game"
    }, {
        "id": "g:21",
        "name": "Game 21",
        "type": "game"
    }, {
        "id": "g:27",
        "name": "Game 27",
        "type": "game"
    }, {
        "id": "g:3",
        "name": "Game 3",
        "type": "game"
    }]
}, {
    "id": "c:141",
    "name": "Estimates length of an object and distance between two given locations.",
    "games": [{
        "id": "g:47",
        "name": "Game 47",
        "type": "screener"
    }, {
        "id": "g:21",
        "name": "Game 21",
        "type": "game"
    }, {
        "id": "g:12",
        "name": "Game 12",
        "type": "game"
    }, {
        "id": "g:35",
        "name": "Game 35",
        "type": "screener"
    }]
}, {
    "id": "c:142",
    "name": "Relates commonly used larger and smaller units of length, weight and volume and converts one to the other.",
    "games": []
}, {
    "id": "c:143",
    "name": "Compare two or more objects by their weight and appreciate the need for a balance",
    "games": [{
        "id": "g:34",
        "name": "Game 34",
        "type": "screener"
    }, {
        "id": "g:23",
        "name": "Game 23",
        "type": "game"
    }, {
        "id": "g:32",
        "name": "Game 32",
        "type": "screener"
    }]
}, {
    "id": "c:144",
    "name": "Compare weights by using a balance",
    "games": [{
        "id": "g:4",
        "name": "Game 4",
        "type": "game"
    }, {
        "id": "g:47",
        "name": "Game 47",
        "type": "screener"
    }, {
        "id": "g:18",
        "name": "Game 18",
        "type": "game"
    }, {
        "id": "g:21",
        "name": "Game 21",
        "type": "game"
    }, {
        "id": "g:20",
        "name": "Game 20",
        "type": "game"
    }]
}, {
    "id": "c:145",
    "name": "Appreciate the conservation of weight",
    "games": []
}, {
    "id": "c:146",
    "name": "weigh objects using balance and standard units; estimate weight of an object and verify using a balance",
    "games": [{
        "id": "g:41",
        "name": "Game 41",
        "type": "screener"
    }, {
        "id": "g:25",
        "name": "Game 25",
        "type": "game"
    }]
}, {
    "id": "c:147",
    "name": "Determines sums and differences of weights",
    "games": [{
        "id": "g:7",
        "name": "Game 7",
        "type": "game"
    }, {
        "id": "g:10",
        "name": "Game 10",
        "type": "game"
    }, {
        "id": "g:5",
        "name": "Game 5",
        "type": "game"
    }, {
        "id": "g:39",
        "name": "Game 39",
        "type": "screener"
    }, {
        "id": "g:36",
        "name": "Game 36",
        "type": "screener"
    }]
}, {
    "id": "c:148",
    "name": "Measurement with non standard metric ",
    "games": [{
        "id": "g:46",
        "name": "Game 46",
        "type": "screener"
    }]
}, {
    "id": "c:149",
    "name": "Estimate volume, compare capacity",
    "games": [{
        "id": "g:19",
        "name": "Game 19",
        "type": "game"
    }, {
        "id": "g:40",
        "name": "Game 40",
        "type": "screener"
    }, {
        "id": "g:12",
        "name": "Game 12",
        "type": "game"
    }]
}, {
    "id": "c:150",
    "name": "Measure volume using non standard measures",
    "games": [{
        "id": "g:31",
        "name": "Game 31",
        "type": "screener"
    }]
}, {
    "id": "c:151",
    "name": "Appreciate the conservation of volume",
    "games": [{
        "id": "g:34",
        "name": "Game 34",
        "type": "screener"
    }, {
        "id": "g:27",
        "name": "Game 27",
        "type": "game"
    }, {
        "id": "g:45",
        "name": "Game 45",
        "type": "screener"
    }, {
        "id": "g:44",
        "name": "Game 44",
        "type": "screener"
    }, {
        "id": "g:3",
        "name": "Game 3",
        "type": "game"
    }]
}, {
    "id": "c:152",
    "name": "Measures volumes of given liquid using containers marked with standard units.",
    "games": [{
        "id": "g:33",
        "name": "Game 33",
        "type": "screener"
    }]
}, {
    "id": "c:153",
    "name": "Determines sums and differences of volumes.",
    "games": [{
        "id": "g:43",
        "name": "Game 43",
        "type": "screener"
    }, {
        "id": "g:18",
        "name": "Game 18",
        "type": "game"
    }, {
        "id": "g:25",
        "name": "Game 25",
        "type": "game"
    }]
}, {
    "id": "c:154",
    "name": "Estimates the volume of a liquid contained in a vessel and verifies by measuring.",
    "games": []
}, {
    "id": "c:155",
    "name": "Converts fractional larger unit into complete smaller units.",
    "games": [{
        "id": "g:29",
        "name": "Game 29",
        "type": "game"
    }, {
        "id": "g:35",
        "name": "Game 35",
        "type": "screener"
    }, {
        "id": "g:44",
        "name": "Game 44",
        "type": "screener"
    }, {
        "id": "g:10",
        "name": "Game 10",
        "type": "game"
    }]
}, {
    "id": "c:156",
    "name": "Distinguish between events occuring in time : earlier and later, long and short duration; compute time intervals",
    "games": [{
        "id": "g:17",
        "name": "Game 17",
        "type": "game"
    }, {
        "id": "g:32",
        "name": "Game 32",
        "type": "screener"
    }, {
        "id": "g:33",
        "name": "Game 33",
        "type": "screener"
    }]
}, {
    "id": "c:157",
    "name": "Learn about parts of a calendar: Familiar with days of the week and months in a year",
    "games": [{
        "id": "g:46",
        "name": "Game 46",
        "type": "screener"
    }, {
        "id": "g:49",
        "name": "Game 49",
        "type": "screener"
    }, {
        "id": "g:14",
        "name": "Game 14",
        "type": "game"
    }]
}, {
    "id": "c:158",
    "name": "Read a calendar to find a day and date",
    "games": [{
        "id": "g:46",
        "name": "Game 46",
        "type": "screener"
    }, {
        "id": "g:49",
        "name": "Game 49",
        "type": "screener"
    }, {
        "id": "g:2",
        "name": "Game 2",
        "type": "game"
    }, {
        "id": "g:8",
        "name": "Game 8",
        "type": "game"
    }, {
        "id": "g:41",
        "name": "Game 41",
        "type": "screener"
    }]
}, {
    "id": "c:159",
    "name": "Read time in the clock",
    "games": [{
        "id": "g:35",
        "name": "Game 35",
        "type": "screener"
    }]
}, {
    "id": "c:160",
    "name": "Sequence events chronologically",
    "games": []
}, {
    "id": "c:161",
    "name": "Compute number of weeks in a year",
    "games": [{
        "id": "g:11",
        "name": "Game 11",
        "type": "game"
    }, {
        "id": "g:49",
        "name": "Game 49",
        "type": "screener"
    }, {
        "id": "g:32",
        "name": "Game 32",
        "type": "screener"
    }]
}, {
    "id": "c:162",
    "name": "Correlate number of days in a year with the number of days in a month; understand leap year",
    "games": [{
        "id": "g:14",
        "name": "Game 14",
        "type": "game"
    }]
}, {
    "id": "c:163",
    "name": "Reads clock time to the nearest hours and minutes.",
    "games": [{
        "id": "g:41",
        "name": "Game 41",
        "type": "screener"
    }, {
        "id": "g:22",
        "name": "Game 22",
        "type": "game"
    }, {
        "id": "g:39",
        "name": "Game 39",
        "type": "screener"
    }, {
        "id": "g:40",
        "name": "Game 40",
        "type": "screener"
    }, {
        "id": "g:15",
        "name": "Game 15",
        "type": "game"
    }]
}, {
    "id": "c:164",
    "name": "Expresses time, using the terms,a.m. and p.m.",
    "games": [{
        "id": "g:5",
        "name": "Game 5",
        "type": "game"
    }, {
        "id": "g:16",
        "name": "Game 16",
        "type": "game"
    }, {
        "id": "g:4",
        "name": "Game 4",
        "type": "game"
    }, {
        "id": "g:45",
        "name": "Game 45",
        "type": "screener"
    }]
}, {
    "id": "c:165",
    "name": "Find approximate time elapsed by forward counting",
    "games": [{
        "id": "g:13",
        "name": "Game 13",
        "type": "game"
    }, {
        "id": "g:16",
        "name": "Game 16",
        "type": "game"
    }, {
        "id": "g:19",
        "name": "Game 19",
        "type": "game"
    }, {
        "id": "g:24",
        "name": "Game 24",
        "type": "game"
    }]
}, {
    "id": "c:166",
    "name": "Computes the number of days between two dates.",
    "games": []
}, {
    "id": "c:167",
    "name": "use addition to subtraction to find time intervals",
    "games": [{
        "id": "g:19",
        "name": "Game 19",
        "type": "game"
    }]
}, {
    "id": "c:168",
    "name": "Determine area and perimeter of single geometrical figures",
    "games": []
}, {
    "id": "c:169",
    "name": "Learn to represent angles numerically",
    "games": [{
        "id": "g:46",
        "name": "Game 46",
        "type": "screener"
    }, {
        "id": "g:1",
        "name": "Game 1",
        "type": "game"
    }, {
        "id": "g:39",
        "name": "Game 39",
        "type": "screener"
    }, {
        "id": "g:7",
        "name": "Game 7",
        "type": "game"
    }, {
        "id": "g:15",
        "name": "Game 15",
        "type": "game"
    }]
}, {
    "id": "c:170",
    "name": "Identify money, handle small amounts of money",
    "games": [{
        "id": "g:41",
        "name": "Game 41",
        "type": "screener"
    }]
}, {
    "id": "c:171",
    "name": "Conversion of rupee to paise, make rate cards and bills",
    "games": []
}, {
    "id": "c:172",
    "name": "Conversion of rupee to paise",
    "games": [{
        "id": "g:26",
        "name": "Game 26",
        "type": "game"
    }]
}, {
    "id": "c:173",
    "name": "Application of money in estimation of addition and subtraction",
    "games": [{
        "id": "g:7",
        "name": "Game 7",
        "type": "game"
    }, {
        "id": "g:20",
        "name": "Game 20",
        "type": "game"
    }]
}, {
    "id": "c:174",
    "name": "Addition as inverse of subtraction - get to 0 using money",
    "games": []
}, {
    "id": "c:175",
    "name": "Add and subtract using small amounts of money mentally",
    "games": [{
        "id": "g:24",
        "name": "Game 24",
        "type": "game"
    }, {
        "id": "g:15",
        "name": "Game 15",
        "type": "game"
    }, {
        "id": "g:45",
        "name": "Game 45",
        "type": "screener"
    }, {
        "id": "g:28",
        "name": "Game 28",
        "type": "game"
    }, {
        "id": "g:17",
        "name": "Game 17",
        "type": "game"
    }]
}, {
    "id": "c:176",
    "name": "Add/subtract using money (upto 50) ",
    "games": []
}, {
    "id": "c:177",
    "name": "addition and subtraction of money upto 1000 (grouping), estimate total and total cost",
    "games": [{
        "id": "g:44",
        "name": "Game 44",
        "type": "screener"
    }, {
        "id": "g:15",
        "name": "Game 15",
        "type": "game"
    }, {
        "id": "g:6",
        "name": "Game 6",
        "type": "game"
    }]
}, {
    "id": "c:178",
    "name": "Apply add/subtract/multiply operations in solving money problems",
    "games": [{
        "id": "g:3",
        "name": "Game 3",
        "type": "game"
    }, {
        "id": "g:1",
        "name": "Game 1",
        "type": "game"
    }, {
        "id": "g:6",
        "name": "Game 6",
        "type": "game"
    }, {
        "id": "g:33",
        "name": "Game 33",
        "type": "screener"
    }, {
        "id": "g:16",
        "name": "Game 16",
        "type": "game"
    }]
}, {
    "id": "c:179",
    "name": "Four operations using money",
    "games": [{
        "id": "g:34",
        "name": "Game 34",
        "type": "screener"
    }, {
        "id": "g:19",
        "name": "Game 19",
        "type": "game"
    }]
}, {
    "id": "c:180",
    "name": "Understand fractions and decimals in context of money",
    "games": []
}, {
    "id": "c:181",
    "name": "Use decimal fractions for money",
    "games": [{
        "id": "g:49",
        "name": "Game 49",
        "type": "screener"
    }, {
        "id": "g:9",
        "name": "Game 9",
        "type": "game"
    }, {
        "id": "g:3",
        "name": "Game 3",
        "type": "game"
    }]
}, {
    "id": "c:182",
    "name": "Identifies right angles in environment. Classifies angles into right, acute and obtuse angles. Represents right angle, acute angle an obtuse angle by drawing and tracing.",
    "games": [{
        "id": "g:38",
        "name": "Game 38",
        "type": "screener"
    }, {
        "id": "g:48",
        "name": "Game 48",
        "type": "screener"
    }, {
        "id": "g:47",
        "name": "Game 47",
        "type": "screener"
    }, {
        "id": "g:14",
        "name": "Game 14",
        "type": "game"
    }, {
        "id": "g:16",
        "name": "Game 16",
        "type": "game"
    }]
}, {
    "id": "c:183",
    "name": "Collect and represent data ",
    "games": [{
        "id": "g:28",
        "name": "Game 28",
        "type": "game"
    }]
}, {
    "id": "c:184",
    "name": "Draw inferences from data",
    "games": [{
        "id": "g:31",
        "name": "Game 31",
        "type": "screener"
    }, {
        "id": "g:39",
        "name": "Game 39",
        "type": "screener"
    }, {
        "id": "g:34",
        "name": "Game 34",
        "type": "screener"
    }]
}, {
    "id": "c:185",
    "name": "Draw inferences",
    "games": [{
        "id": "g:22",
        "name": "Game 22",
        "type": "game"
    }, {
        "id": "g:25",
        "name": "Game 25",
        "type": "game"
    }, {
        "id": "g:31",
        "name": "Game 31",
        "type": "screener"
    }, {
        "id": "g:2",
        "name": "Game 2",
        "type": "game"
    }, {
        "id": "g:6",
        "name": "Game 6",
        "type": "game"
    }]
}, {
    "id": "c:186",
    "name": "Collect and represent data -tally mark, pictograph",
    "games": [{
        "id": "g:6",
        "name": "Game 6",
        "type": "game"
    }, {
        "id": "g:29",
        "name": "Game 29",
        "type": "game"
    }]
}, {
    "id": "c:187",
    "name": "Collect and represent data - bar graph",
    "games": [{
        "id": "g:31",
        "name": "Game 31",
        "type": "screener"
    }]
}, {
    "id": "c:188",
    "name": "Collect and represent data - pictograph, bar graph",
    "games": [{
        "id": "g:7",
        "name": "Game 7",
        "type": "game"
    }]
}]
