{
  "definitionNodes": [
    {
      "objectType": "LangSearch",
      "properties": [
        {
          "propertyName": "startWith",
          "title": "Starts With",
          "description": "",
          "category": "languageSearch",
          "dataType": "Text",
          "range": [],
          "required": false,
          "indexed": true,
          "displayProperty": "Editable",
          "defaultValue": "",
          "renderingHints": {
            "inputType": "text",
            "order": 1
          }
        },
        {
          "propertyName": "endsWith",
          "title": "Ends With",
          "description": "",
          "category": "languageSearch",
          "dataType": "Text",
          "range": [],
          "required": false,
          "indexed": true,
          "displayProperty": "Editable",
          "defaultValue": "",
          "renderingHints": {
            "inputType": "text",
            "order": 2
          }
        },
        {
          "propertyName": "lemmaValue",
          "title": "Word Lemma",
          "description": "",
          "category": "languageSearch",
          "dataType": "Text",
          "range": [],
          "required": false,
          "indexed": true,
          "displayProperty": "Editable",
          "defaultValue": "",
          "renderingHints": {
            "inputType": "text",
            "order": 3
          }
        },
        {
          "propertyName": "minOrthographicComplexity",
          "title": "Min. Orthographic Complexity",
          "description": "",
          "category": "languageSearch",
          "dataType": "Text",
          "range": [],
          "required": false,
          "indexed": false,
          "displayProperty": "Editable",
          "defaultValue": "",
          "renderingHints": {
            "inputType": "text",
            "order": 4
          }
        },
        {
          "propertyName": "maxOrthographicComplexity",
          "title": "Max. Orthographic Complexity",
          "description": "",
          "category": "languageSearch",
          "dataType": "Text",
          "range": [],
          "required": false,
          "indexed": true,
          "displayProperty": "Editable",
          "defaultValue": "",
          "renderingHints": {
            "inputType": "text",
            "order": 5
          }
        },
        {
          "propertyName": "orthographicComplexityValue",
          "title": "Exact Orthographic Complexity",
          "description": "",
          "category": "languageSearch",
          "dataType": "Text",
          "range": [],
          "required": false,
          "indexed": false,
          "displayProperty": "Editable",
          "defaultValue": "",
          "renderingHints": {
            "inputType": "text",
            "order": 7
          }
        },
        {
          "propertyName": "minPhonologicComplexity",
          "title": "Min. Phonologic Complexity",
          "description": "",
          "category": "languageSearch",
          "dataType": "Text",
          "range": [],
          "required": false,
          "indexed": false,
          "displayProperty": "Editable",
          "defaultValue": "",
          "renderingHints": {
            "inputType": "text",
            "order": 8
          }
        },
        {
          "propertyName": "maxPhonologicComplexity",
          "title": "Max. Phonologic Complexity",
          "description": "",
          "category": "languageSearch",
          "dataType": "Text",
          "range": [],
          "required": false,
          "indexed": false,
          "displayProperty": "Editable",
          "defaultValue": "",
          "renderingHints": {
            "inputType": "text",
            "order": 8
          }
        },
        {
          "propertyName": "phonologicComplexityValue",
          "title": "Exact Phonologic Complexity",
          "description": "",
          "category": "languageSearch",
          "dataType": "Text",
          "range": [],
          "required": false,
          "indexed": true,
          "displayProperty": "Editable",
          "defaultValue": "Draft",
          "renderingHints": {
            "inputType": "text",
            "order": 9
          }
        },
        {
          "propertyName": "minSyllableCount",
          "title": "Min. Syllable Count",
          "description": "",
          "category": "languageSearch",
          "dataType": "Text",
          "range": [],
          "required": false,
          "indexed": false,
          "displayProperty": "Editable",
          "defaultValue": "",
          "renderingHints": {
            "inputType": "text",
            "order": 9
          }
        },
        {
          "propertyName": "maxSyllableCount",
          "title": "Max. Syllable Count",
          "description": "",
          "category": "languageSearch",
          "dataType": "Text",
          "range": [],
          "required": false,
          "indexed": false,
          "displayProperty": "Editable",
          "defaultValue": "",
          "renderingHints": {
            "inputType": "text",
            "order": 12
          }
        },
        {
          "propertyName": "syllableCountValue",
          "title": "Exact Syllable Count",
          "description": "",
          "category": "languageSearch",
          "dataType": "Text",
          "range": [],
          "required": false,
          "indexed": false,
          "displayProperty": "Editable",
          "defaultValue": "",
          "renderingHints": {
            "inputType": "table",
            "order": 10
          }
        },
        {
          "propertyName": "sourceType",
          "title": "Type of Word Source",
          "description": "",
          "category": "languageSearch",
          "dataType": "Select",
          "range": [
            "textbooks",
            "wordnets"
          ],
          "required": false,
          "indexed": true,
          "displayProperty": "Editable",
          "defaultValue": "",
          "renderingHints": {
            "inputType": "select",
            "order": 14
          }
        },
        {
          "propertyName": "source",
          "title": "Word Source",
          "description": "",
          "category": "languageSearch",
          "dataType": "Select",
          "range": [
            "IndoWordnet",
            "Karnataka Govt Textbooks",
            "Rajasthan Textbooks"
          ],
          "required": false,
          "indexed": true,
          "displayProperty": "Editable",
          "defaultValue": "",
          "renderingHints": {
            "inputType": "select",
            "order": 14
          }
        },
        {
          "propertyName": "wordPOS",
          "title": "Word's Parts of Speech",
          "description": "",
          "category": "languageSearch",
          "dataType": "Select",
          "range": [
            "vm",
            "nn",
            "nst",
            "wq",
            "prp",
            "dem",
            "cc",
            "jj",
            "rb",
            "qc",
            "rp",
            "qf"
          ],
          "required": false,
          "indexed": false,
          "displayProperty": "Editable",
          "defaultValue": "",
          "renderingHints": {
            "inputType": "select",
            "order": 14
          }
        },
        {
          "propertyName": "grade",
          "title": "Grade",
          "description": "",
          "category": "languageSearch",
          "dataType": "Select",
          "range": [
            1,
            2,
            3,
            4,
            5
          ],
          "required": false,
          "indexed": false,
          "displayProperty": "Editable",
          "defaultValue": "",
          "renderingHints": {
            "inputType": "select",
            "order": 14
          }
        },
        {
          "propertyName": "wordList",
          "title": "Word List",
          "description": "",
          "category": "languageSearch",
          "dataType": "Text",
          "range": [],
          "required": false,
          "indexed": false,
          "displayProperty": "Editable",
          "defaultValue": "",
          "renderingHints": {
            "inputType": "text",
            "order": 14
          }
        }
      ],
      "inRelations": [],
      "outRelations": [],
      "systemTags": []
    }
  ]
}
